autolabel/__init__.py
autolabel/__main__.py
autolabel/classifier.py
autolabel/cli.py
autolabel/image.py
autolabel/classifier/__init__.py
autolabel/classifier/base.py
autolabel/classifier/resnet.py
autolabel/classifier/resnetlabels.py
autolabel/models/__init__.py
autolabel/models/resnet.py
autolabel/models/resnetlabels.py
autolabel-0.0.1.dist-info/LICENSE
autolabel-0.0.1.dist-info/METADATA
autolabel-0.0.1.dist-info/WHEEL
autolabel-0.0.1.dist-info/entry_points.txt
autolabel-0.0.1.dist-info/top_level.txt
autolabel-0.0.1.dist-info/RECORD
