Metadata-Version: 2.1
Name: autolabel
Version: 0.0.1
Summary: Autolabel is an image labeling tool using Neural Network
Home-page: https://github.com/walwe/autolabel
Author: walwe
License: UNKNOWN
Platform: UNKNOWN
Classifier: Programming Language :: Python :: 3
Classifier: License :: OSI Approved :: MIT License
Classifier: Operating System :: OS Independent
Requires-Python: >=3.6
Requires-Dist: click
Requires-Dist: more-itertools
Requires-Dist: torchvision
Requires-Dist: torch
Requires-Dist: pillow
Requires-Dist: numpy
